{
"type": "FeatureCollection",
"name": "BODOVE_POLE_T",
"features": [
{ "type": "Feature", "properties": { "ID": "1", "ID_2": "1420871731", "TYPPPD_KOD": "1016", "KATUZE_KOD": 600822, "TEXT_KM": "513", "PBPP_ID": "8399731", "PZBPP_ID": null, "ZBPP_ID": null, "ROTACE": 0, "VZ_BOD": "CR", "MERITKO": "1" }, "geometry": { "type": "Point", "coordinates": [ 16.642015054398023, 49.524371670335995 ] } },
{ "type": "Feature", "properties": { "ID": "2", "ID_2": "1190904731", "TYPPPD_KOD": "1016", "KATUZE_KOD": 600822, "TEXT_KM": "16", "PBPP_ID": null, "PZBPP_ID": null, "ZBPP_ID": "36832020", "ROTACE": 0, "VZ_BOD": "CR", "MERITKO": "1" }, "geometry": { "type": "Point", "coordinates": [ 16.647609757314704, 49.530234624261695 ] } },
{ "type": "Feature", "properties": { "ID": "3", "ID_2": "1190905731", "TYPPPD_KOD": "1016", "KATUZE_KOD": 600822, "TEXT_KM": "519", "PBPP_ID": "8903731", "PZBPP_ID": null, "ZBPP_ID": null, "ROTACE": 0, "VZ_BOD": "BL", "MERITKO": "1" }, "geometry": { "type": "Point", "coordinates": [ 16.636358595934951, 49.523304908722686 ] } },
{ "type": "Feature", "properties": { "ID": "4", "ID_2": "1190002731", "TYPPPD_KOD": "1016", "KATUZE_KOD": 600822, "TEXT_KM": "506", "PBPP_ID": "10478731", "PZBPP_ID": null, "ZBPP_ID": null, "ROTACE": 0, "VZ_BOD": "BL", "MERITKO": "1" }, "geometry": { "type": "Point", "coordinates": [ 16.643147678540359, 49.527701377358213 ] } },
{ "type": "Feature", "properties": { "ID": "5", "ID_2": "1190003731", "TYPPPD_KOD": "1016", "KATUZE_KOD": 600822, "TEXT_KM": "510", "PBPP_ID": "10479731", "PZBPP_ID": null, "ZBPP_ID": null, "ROTACE": 0, "VZ_BOD": "BL", "MERITKO": "1" }, "geometry": { "type": "Point", "coordinates": [ 16.642575875506495, 49.525636946012497 ] } },
{ "type": "Feature", "properties": { "ID": "6", "ID_2": "1190004731", "TYPPPD_KOD": "1016", "KATUZE_KOD": 600822, "TEXT_KM": "511", "PBPP_ID": "10480731", "PZBPP_ID": null, "ZBPP_ID": null, "ROTACE": 0, "VZ_BOD": "BL", "MERITKO": "1" }, "geometry": { "type": "Point", "coordinates": [ 16.642345879062848, 49.525691104998046 ] } },
{ "type": "Feature", "properties": { "ID": "7", "ID_2": "1190175731", "TYPPPD_KOD": "1016", "KATUZE_KOD": 600822, "TEXT_KM": "518", "PBPP_ID": "8902731", "PZBPP_ID": null, "ZBPP_ID": null, "ROTACE": 0, "VZ_BOD": "BL", "MERITKO": "1" }, "geometry": { "type": "Point", "coordinates": [ 16.643005495730549, 49.522266547563476 ] } },
{ "type": "Feature", "properties": { "ID": "8", "ID_2": "1190178731", "TYPPPD_KOD": "1016", "KATUZE_KOD": 600822, "TEXT_KM": "505", "PBPP_ID": "10477731", "PZBPP_ID": null, "ZBPP_ID": null, "ROTACE": 0, "VZ_BOD": "BL", "MERITKO": "1" }, "geometry": { "type": "Point", "coordinates": [ 16.643577335649518, 49.52778591530943 ] } }
]
}
